qcodes/__init__.py
qcodes/_version.py
qcodes/interactive_widget.py
qcodes/py.typed
qcodes/station.py
qcodes/calibrations/__init__.py
qcodes/calibrations/keithley.py
qcodes/configuration/__init__.py
qcodes/configuration/config.py
qcodes/configuration/qcodesrc.json
qcodes/configuration/qcodesrc_schema.json
qcodes/dataset/__init__.py
qcodes/dataset/data_export.py
qcodes/dataset/data_set.py
qcodes/dataset/data_set_cache.py
qcodes/dataset/data_set_in_memory.py
qcodes/dataset/data_set_info.py
qcodes/dataset/data_set_protocol.py
qcodes/dataset/database_extract_runs.py
qcodes/dataset/database_fix_functions.py
qcodes/dataset/dataset_helpers.py
qcodes/dataset/experiment_container.py
qcodes/dataset/experiment_settings.py
qcodes/dataset/export_config.py
qcodes/dataset/guid_helpers.py
qcodes/dataset/guids.py
qcodes/dataset/json_exporter.py
qcodes/dataset/legacy_import.py
qcodes/dataset/measurement_extensions.py
qcodes/dataset/measurements.py
qcodes/dataset/plotting.py
qcodes/dataset/snapshot_utils.py
qcodes/dataset/subscriber.py
qcodes/dataset/threading.py
qcodes/dataset/descriptions/__init__.py
qcodes/dataset/descriptions/dependencies.py
qcodes/dataset/descriptions/detect_shapes.py
qcodes/dataset/descriptions/param_spec.py
qcodes/dataset/descriptions/rundescriber.py
qcodes/dataset/descriptions/versioning/__init__.py
qcodes/dataset/descriptions/versioning/converters.py
qcodes/dataset/descriptions/versioning/rundescribertypes.py
qcodes/dataset/descriptions/versioning/serialization.py
qcodes/dataset/descriptions/versioning/v0.py
qcodes/dataset/dond/__init__.py
qcodes/dataset/dond/do2d_retrace.py
qcodes/dataset/dond/do_0d.py
qcodes/dataset/dond/do_1d.py
qcodes/dataset/dond/do_2d.py
qcodes/dataset/dond/do_nd.py
qcodes/dataset/dond/do_nd_utils.py
qcodes/dataset/dond/sweeps.py
qcodes/dataset/exporters/__init__.py
qcodes/dataset/exporters/export_info.py
qcodes/dataset/exporters/export_to_csv.py
qcodes/dataset/exporters/export_to_pandas.py
qcodes/dataset/exporters/export_to_xarray.py
qcodes-0.54.4.dist-info/licenses/LICENSE
qcodes-0.54.4.dist-info/METADATA
qcodes-0.54.4.dist-info/WHEEL
qcodes-0.54.4.dist-info/entry_points.txt
qcodes-0.54.4.dist-info/top_level.txt
qcodes-0.54.4.dist-info/RECORD
